odoo/addons/stock_release_channel/README.rst
odoo/addons/stock_release_channel/__init__.py
odoo/addons/stock_release_channel/__manifest__.py
odoo/addons/stock_release_channel/data/ir_cron_data.xml
odoo/addons/stock_release_channel/data/queue_job_data.xml
odoo/addons/stock_release_channel/data/stock_release_channel_data.xml
odoo/addons/stock_release_channel/i18n/it.po
odoo/addons/stock_release_channel/i18n/stock_release_channel.pot
odoo/addons/stock_release_channel/models/__init__.py
odoo/addons/stock_release_channel/models/stock_move.py
odoo/addons/stock_release_channel/models/stock_picking.py
odoo/addons/stock_release_channel/models/stock_release_channel.py
odoo/addons/stock_release_channel/readme/CONFIGURE.rst
odoo/addons/stock_release_channel/readme/CONTRIBUTORS.rst
odoo/addons/stock_release_channel/readme/CREDITS.rst
odoo/addons/stock_release_channel/readme/DESCRIPTION.rst
odoo/addons/stock_release_channel/readme/USAGE.rst
odoo/addons/stock_release_channel/security/stock_release_channel.xml
odoo/addons/stock_release_channel/static/description/icon.png
odoo/addons/stock_release_channel/static/description/index.html
odoo/addons/stock_release_channel/static/src/js/progressbar_fractional_widget.js
odoo/addons/stock_release_channel/static/src/scss/stock_release_channel.scss
odoo/addons/stock_release_channel/tests/__init__.py
odoo/addons/stock_release_channel/tests/common.py
odoo/addons/stock_release_channel/tests/test_channel_action.py
odoo/addons/stock_release_channel/tests/test_channel_computed_fields.py
odoo/addons/stock_release_channel/tests/test_channel_release_batch.py
odoo/addons/stock_release_channel/tests/test_release_channel.py
odoo/addons/stock_release_channel/tests/test_release_channel_lifecycle.py
odoo/addons/stock_release_channel/views/assets.xml
odoo/addons/stock_release_channel/views/stock_picking_views.xml
odoo/addons/stock_release_channel/views/stock_release_channel_views.xml
odoo14_addon_stock_release_channel-14.0.2.3.1.dist-info/METADATA
odoo14_addon_stock_release_channel-14.0.2.3.1.dist-info/WHEEL
odoo14_addon_stock_release_channel-14.0.2.3.1.dist-info/top_level.txt
odoo14_addon_stock_release_channel-14.0.2.3.1.dist-info/RECORD
