Metadata-Version: 2.1
Name: odoo14-addon-stock_release_channel
Version: 14.0.2.3.1
Summary: Manage workload in WMS with release channels
Home-page: https://github.com/OCA/wms
Author: Camptocamp, ACSONE SA/NV, Odoo Community Association (OCA)
Author-email: support@odoo-community.org
License: AGPL-3
Classifier: Programming Language :: Python
Classifier: Framework :: Odoo
Classifier: Framework :: Odoo :: 14.0
Classifier: License :: OSI Approved :: GNU Affero General Public License v3
Classifier: Development Status :: 4 - Beta
Requires-Python: >=3.6
Requires-Dist: odoo14-addon-queue-job
Requires-Dist: odoo14-addon-stock-available-to-promise-release
Requires-Dist: odoo<14.1dev,>=14.0a
